csvchatbot/__init__.py
csvchatbot/agent.py
csvchatbot-0.1.0.dist-info/licenses/LICENSE
csvchatbot-0.1.0.dist-info/METADATA
csvchatbot-0.1.0.dist-info/WHEEL
csvchatbot-0.1.0.dist-info/top_level.txt
csvchatbot-0.1.0.dist-info/RECORD
